CkInoDriveAPI/IO.py
CkInoDriveAPI/__init__.py
CkInoDriveAPI/_version.py
CkInoDriveAPI/callback.py
CkInoDriveAPI/ck_ca.crt
CkInoDriveAPI/defines.py
CkInoDriveAPI/discoverLan.py
CkInoDriveAPI/discoverWs.py
CkInoDriveAPI/file.py
CkInoDriveAPI/inoDrive.py
CkInoDriveAPI/sysControl.py
CkInoDriveAPI/userApp.py
CkInoDriveAPI/utils.py
CkInoDriveAPI/wsHandle.py
CK_InoDrive_API-1.0.1.dist-info/LICENSE.txt
CK_InoDrive_API-1.0.1.dist-info/METADATA
CK_InoDrive_API-1.0.1.dist-info/README.txt
CK_InoDrive_API-1.0.1.dist-info/WHEEL
CK_InoDrive_API-1.0.1.dist-info/top_level.txt
CK_InoDrive_API-1.0.1.dist-info/RECORD
