Metadata-Version: 2.1
Name: CK-InoDrive-API
Version: 1.0.1
Summary: InoDrive API Library
Home-page: https://cardinalkinetic.com
Author: Cardinal Kinetic
Author-email: support@cardinalkinetic.com
License: https://www.cardinalkinetic.com/user-manual/api/inodrive-py
Project-URL: Documentation, https://www.cardinalkinetic.com/user-manual/api/inodrive-py
Keywords: InoWorx InoDrive InoSync MotionControl ServoControl
Classifier: Development Status :: 5 - Production/Stable
Classifier: Intended Audience :: Developers
Classifier: Operating System :: Microsoft :: Windows
Classifier: Topic :: Scientific/Engineering
Classifier: Programming Language :: Python :: 3
Classifier: Programming Language :: Python :: 3.10
Classifier: Programming Language :: Python :: 3.12
License-File: LICENSE.txt
License-File: README.txt
Requires-Dist: websocket-client ==1.8.0
Requires-Dist: ifaddr ==0.2.0
Requires-Dist: msgpack ==1.1.0
